cloud_scanner_generic/__init__.py
cloud_scanner_generic/version.py
cloud_scanner_generic/config/__init__.py
cloud_scanner_generic/config/elastic_search_config.py
cloud_scanner_generic/config/mysql_config.py
cloud_scanner_generic/services/__init__.py
cloud_scanner_generic/services/elastic_search.py
cloud_scanner_generic/services/errors.py
cloud_scanner_generic/services/mysql_resource_storage.py
cloud_scanner_generic/services/request_helper.py
cloud_scanner_generic/services/rest_storage_service.py
cloud_scanner_generic/simulators/__init__.py
cloud_scanner_generic/simulators/resource_service_simulator.py
tests/__init__.py
tests/test_elasticsearch.py
tests/test_mysql_storage.py
tests/test_request_helper.py
tests/test_rest_resource_storage.py
tests/unittest_base.py
cloud_scanner_generic-0.1.2.dist-info/LICENSE
cloud_scanner_generic-0.1.2.dist-info/METADATA
cloud_scanner_generic-0.1.2.dist-info/WHEEL
cloud_scanner_generic-0.1.2.dist-info/top_level.txt
cloud_scanner_generic-0.1.2.dist-info/RECORD
