Metadata-Version: 2.1
Name: cloud-scanner-generic
Version: 0.1.2
Summary: Generic utilities for scanning cloud resources
Home-page: https://microsoft.github.io/cloud-scanner-generic
Author: Microsoft
Author-email: tanner.barlow@microsoft.com,wallace.breza@microsoft.com
License: MIT
Platform: UNKNOWN
Requires-Dist: elasticsearch
Requires-Dist: PyMySQL
Requires-Dist: requests
